langchain_builtsimple/__init__.py
langchain_builtsimple/retrievers.py
langchain_builtsimple/tools.py
langchain_builtsimple-0.1.0.dist-info/METADATA
langchain_builtsimple-0.1.0.dist-info/WHEEL
langchain_builtsimple-0.1.0.dist-info/licenses/LICENSE
langchain_builtsimple-0.1.0.dist-info/RECORD
