Metadata-Version: 2.4
Name: langchain-builtsimple
Version: 0.1.0
Summary: LangChain integration for Built-Simple research APIs (PubMed & ArXiv)
Project-URL: Homepage, https://github.com/built-simple/langchain-builtsimple
Project-URL: Documentation, https://github.com/built-simple/langchain-builtsimple#readme
Project-URL: Repository, https://github.com/built-simple/langchain-builtsimple
Project-URL: Issues, https://github.com/built-simple/langchain-builtsimple/issues
Author-email: Built-Simple <dev@built-simple.ai>
License-Expression: MIT
License-File: LICENSE
Keywords: arxiv,langchain,pubmed,rag,research,retrieval
Classifier: Development Status :: 4 - Beta
Classifier: Intended Audience :: Developers
Classifier: Intended Audience :: Science/Research
Classifier: License :: OSI Approved :: MIT License
Classifier: Programming Language :: Python :: 3
Classifier: Programming Language :: Python :: 3.9
Classifier: Programming Language :: Python :: 3.10
Classifier: Programming Language :: Python :: 3.11
Classifier: Programming Language :: Python :: 3.12
Classifier: Topic :: Scientific/Engineering
Classifier: Topic :: Scientific/Engineering :: Artificial Intelligence
Requires-Python: >=3.9
Requires-Dist: httpx>=0.25.0
Requires-Dist: langchain-core>=0.2.0
Provides-Extra: dev
Requires-Dist: langchain-openai>=0.1.0; extra == 'dev'
Requires-Dist: langchain>=0.2.0; extra == 'dev'
Requires-Dist: pytest-asyncio>=0.21; extra == 'dev'
Requires-Dist: pytest>=7.0; extra == 'dev'
